graphene_cruddals/__init__.py
graphene_cruddals/main.py
graphene_cruddals/operation_fields/__init__.py
graphene_cruddals/operation_fields/main.py
graphene_cruddals/registry/__init__.py
graphene_cruddals/registry/registry_global.py
graphene_cruddals/types/__init__.py
graphene_cruddals/types/error_types.py
graphene_cruddals/types/main.py
graphene_cruddals/types/utils.py
graphene_cruddals/utils/__init__.py
graphene_cruddals/utils/main.py
graphene_cruddals/utils/typing/__init__.py
graphene_cruddals/utils/typing/custom_typing.py
graphene_cruddals-0.2.13.dist-info/LICENSE
graphene_cruddals-0.2.13.dist-info/METADATA
graphene_cruddals-0.2.13.dist-info/WHEEL
graphene_cruddals-0.2.13.dist-info/top_level.txt
graphene_cruddals-0.2.13.dist-info/RECORD
